{"name":"**Beach**","nameHtml":"<p><strong>Beach</strong></p>\n","safeName":"Beach-3","coordinates":{"irishGrid":{"sheet":"S","eastings":"754","northings":"030"},"fullIrishGrid":{"sheet":"","eastings":"275400","northings":"103000"},"tmcGrid":{"sheet":"","eastings":"675334.115","northings":"603055.144"},"geo":{"lat":"52.17416285","long":-6.89858895}},"cursor":28429,"description":"<p><strong>Beach</strong> S754-030          Sheet 76 Just W of the popular Templetown Inn, a pub-grub establishment, there is no access from the roadside but there is a good sandy beach.</p>\n","costalZone":"**The South Coast**"}